pyberries/__init__.py
pyberries/data/DataFrame_util.py
pyberries/data/DatasetPool.py
pyberries/data/Fitting.py
pyberries/data/__init__.py
pyberries/data/util.py
pyberries/metrics/Metrics.py
pyberries/metrics/__init__.py
pyberries/plots/Plot_object_elements.py
pyberries/plots/Plot_presets.py
pyberries/plots/Plot_utilities.py
pyberries/plots/Plots.py
pyberries/plots/__init__.py
pyberries/stats/__init__.py
pyberries/stats/information_criteria.py
pyberries/stats/test_statistics.py
PyBerries-0.2.26.dist-info/LICENSE
PyBerries-0.2.26.dist-info/METADATA
PyBerries-0.2.26.dist-info/WHEEL
PyBerries-0.2.26.dist-info/top_level.txt
PyBerries-0.2.26.dist-info/RECORD
