Metadata-Version: 2.1
Name: PyBerries
Version: 0.2.26
Summary: Processing of Bacmman measurement tables
Home-page: https://gitlab.com/MEKlab/pyberries
Author: Daniel Thedie
Author-email: daniel.thedie@ed.ac.uk
Requires-Python: >=3.9
License-File: LICENSE
Requires-Dist: numpy>=1.24.3
Requires-Dist: scipy>=1.10
Requires-Dist: pandas>=2.0
Requires-Dist: matplotlib>=3.7
Requires-Dist: tifffile>=2023.4.12
Requires-Dist: h5py>=3.8.0
Requires-Dist: seaborn>=0.13.0
Requires-Dist: pybacmman>=0.6.1
Requires-Dist: IPython>=8.13.2
Requires-Dist: scikit-learn>=1.0.2
